posneg/__init__.py
posneg/__main__.py
posneg/core.py
posneglib-0.1.0.dist-info/licenses/LICENSE
posneglib-0.1.0.dist-info/METADATA
posneglib-0.1.0.dist-info/WHEEL
posneglib-0.1.0.dist-info/entry_points.txt
posneglib-0.1.0.dist-info/top_level.txt
posneglib-0.1.0.dist-info/RECORD
