Metadata-Version: 2.4
Name: PosNegLib
Version: 0.1.0
Summary: Check if a number is positive, negative, or zero
Author: Ali Alsheikh
Author-email: Ali Alsheikh <a77561289@gmail.com>
License: 
Requires-Python: >=3.13
License-File: LICENSE
Dynamic: author
Dynamic: license-file
Dynamic: requires-python
